{
    "frames" : [
        {
            "arm" : [
                0.0,
                -1.396,
                -0.0,
                -0.0,
                -0.0,
                -0.0,
                -0.0,
                1.396,
                0.0,
                -0.0,
                0.0,
                0.0
            ],
            "head_waist" : [
                0.0,
                -0.0,
                -0.0,
                0.0
            ],
            "timeline" : 0.0
        },
        {
            "arm" : [
                0.0,
                -1.396,
                -0.0,
                -0.0,
                -0.0,
                -0.0,
                -0.0,
                1.396,
                0.0,
                0.0,
                -0.0,
                0.0
            ],
            "head_waist" : [
                0.0,
                -0.0,
                -0.0,
                0.0
            ],
            "timeline" : 0.02
        },
        {
            "arm" : [
                0.0,
                -1.396,
                -0.0,
                -0.0,
                -0.0,
                -0.0,
                -0.0,
                1.395,
                0.001,
                0.001,
                -0.0,
                0.0
            ],
            "head_waist" : [
                0.0,
                -0.0,
                -0.0,
                0.0
            ],
            "timeline" : 0.04
        },
        {
            "arm" : [
                0.0,
                -1.396,
                -0.0,
                -0.0,
                -0.0,
                -0.0,
                -0.0,
                1.389,
                0.005,
                0.004,
                -0.001,
                0.0
            ],
            "head_waist" : [
                0.0,
                -0.0,
                -0.0,
                0.0
            ],
            "timeline" : 0.06
        },
        {
            "arm" : [
                0.0,
                -1.396,
                -0.0,
                -0.0,
                -0.0,
                -0.0,
                -0.001,
                1.378,
                0.013,
                0.01,
                -0.003,
                0.0
            ],
            "head_waist" : [
                0.0,
                -0.0,
                -0.0,
                0.0
            ],
            "timeline" : 0.08
        },
        {
            "arm" : [
                0.0,
                -1.396,
                -0.0,
                -0.0,
                -0.0,
                -0.0,
                -0.002,
                1.36,
                0.027,
                0.021,
                -0.006,
                0.0
            ],
            "head_waist" : [
                0.0,
                -0.0,
                -0.0,
                0.0
            ],
            "timeline" : 0.1
        },
        {
            "arm" : [
                0.0,
                -1.396,
                -0.0,
                -0.0,
                -0.0,
                -0.0,
                -0.002,
                1.348,
                0.037,
                0.028,
                -0.008,
                0.0
            ],
            "head_waist" : [
                0.0,
                -0.0,
                -0.0,
                0.0
            ],
            "timeline" : 0.12
        },
        {
            "arm" : [
                0.0,
                -1.396,
                -0.0,
                -0.0,
                -0.0,
                -0.0,
                -0.004,
                1.297,
                0.075,
                0.058,
                -0.017,
                0.0
            ],
            "head_waist" : [
                0.0,
                -0.0,
                -0.0,
                0.0
            ],
            "timeline" : 0.14
        },
        {
            "arm" : [
                0.0,
                -1.396,
                -0.0,
                -0.0,
                -0.0,
                -0.0,
                -0.005,
                1.275,
                0.091,
                0.071,
                -0.02,
                0.0
            ],
            "head_waist" : [
                0.0,
                -0.0,
                -0.0,
                0.0
            ],
            "timeline" : 0.16
        },
        {
            "arm" : [
                0.0,
                -1.396,
                -0.0,
                -0.0,
                -0.0,
                -0.0,
                -0.008,
                1.195,
                0.151,
                0.117,
                -0.034,
                0.0
            ],
            "head_waist" : [
                0.0,
                -0.0,
                -0.0,
                0.0
            ],
            "timeline" : 0.18
        },
        {
            "arm" : [
                0.0,
                -1.396,
                -0.0,
                -0.0,
                -0.0,
                -0.0,
                -0.01,
                1.163,
                0.175,
                0.136,
                -0.039,
                0.0
            ],
            "head_waist" : [
                0.0,
                -0.0,
                -0.0,
                0.0
            ],
            "timeline" : 0.2
        },
        {
            "arm" : [
                0.0,
                -1.396,
                -0.0,
                -0.0,
                -0.0,
                -0.0,
                -0.014,
                1.055,
                0.256,
                0.199,
                -0.057,
                0.0
            ],
            "head_waist" : [
                0.0,
                -0.0,
                -0.0,
                0.0
            ],
            "timeline" : 0.22
        },
        {
            "arm" : [
                0.0,
                -1.396,
                -0.0,
                -0.0,
                -0.0,
                -0.0,
                -0.016,
                1.014,
                0.287,
                0.223,
                -0.064,
                0.0
            ],
            "head_waist" : [
                0.0,
                -0.0,
                -0.0,
                0.0
            ],
            "timeline" : 0.24
        },
        {
            "arm" : [
                0.0,
                -1.396,
                -0.0,
                -0.0,
                -0.0,
                -0.0,
                -0.021,
                0.88,
                0.387,
                0.301,
                -0.086,
                0.0
            ],
            "head_waist" : [
                0.0,
                -0.0,
                -0.0,
                0.0
            ],
            "timeline" : 0.26
        },
        {
            "arm" : [
                0.0,
                -1.396,
                -0.0,
                -0.0,
                -0.0,
                -0.0,
                -0.024,
                0.832,
                0.423,
                0.329,
                -0.094,
                0.0
            ],
            "head_waist" : [
                0.0,
                -0.0,
                -0.0,
                0.0
            ],
            "timeline" : 0.28
        },
        {
            "arm" : [
                0.0,
                -1.396,
                -0.0,
                -0.0,
                -0.0,
                -0.0,
                -0.03,
                0.679,
                0.538,
                0.418,
                -0.12,
                0.0
            ],
            "head_waist" : [
                0.0,
                -0.0,
                -0.0,
                0.0
            ],
            "timeline" : 0.3
        },
        {
            "arm" : [
                0.0,
                -1.396,
                -0.0,
                -0.0,
                -0.0,
                -0.0,
                -0.032,
                0.626,
                0.578,
                0.449,
                -0.128,
                0.0
            ],
            "head_waist" : [
                0.0,
                -0.0,
                -0.0,
                0.0
            ],
            "timeline" : 0.32
        },
        {
            "arm" : [
                0.0,
                -1.396,
                -0.0,
                -0.0,
                -0.0,
                -0.0,
                -0.037,
                0.517,
                0.66,
                0.513,
                -0.147,
                0.0
            ],
            "head_waist" : [
                0.0,
                -0.0,
                -0.0,
                0.0
            ],
            "timeline" : 0.34
        },
        {
            "arm" : [
                0.0,
                -1.396,
                -0.0,
                -0.0,
                -0.0,
                -0.0,
                -0.044,
                0.349,
                0.785,
                0.611,
                -0.175,
                0.0
            ],
            "head_waist" : [
                0.0,
                -0.0,
                -0.0,
                0.0
            ],
            "timeline" : 0.36
        },
        {
            "arm" : [
                0.0,
                -1.396,
                -0.0,
                -0.0,
                -0.0,
                -0.0,
                -0.046,
                0.293,
                0.827,
                0.644,
                -0.184,
                0.0
            ],
            "head_waist" : [
                0.0,
                -0.0,
                -0.0,
                0.0
            ],
            "timeline" : 0.38
        },
        {
            "arm" : [
                0.0,
                -1.396,
                -0.0,
                -0.0,
                -0.0,
                -0.0,
                -0.053,
                0.127,
                0.952,
                0.741,
                -0.212,
                0.0
            ],
            "head_waist" : [
                0.0,
                -0.0,
                -0.0,
                0.0
            ],
            "timeline" : 0.4
        },
        {
            "arm" : [
                0.0,
                -1.396,
                -0.0,
                -0.0,
                -0.0,
                -0.0,
                -0.055,
                0.072,
                0.993,
                0.772,
                -0.221,
                0.0
            ],
            "head_waist" : [
                0.0,
                -0.0,
                -0.0,
                0.0
            ],
            "timeline" : 0.42
        },
        {
            "arm" : [
                0.0,
                -1.396,
                -0.0,
                -0.0,
                -0.0,
                -0.0,
                -0.062,
                -0.084,
                1.11,
                0.864,
                -0.247,
                0.0
            ],
            "head_waist" : [
                0.0,
                -0.0,
                -0.0,
                0.0
            ],
            "timeline" : 0.44
        },
        {
            "arm" : [
                0.0,
                -1.396,
                -0.0,
                -0.0,
                -0.0,
                -0.0,
                -0.064,
                -0.134,
                1.148,
                0.893,
                -0.255,
                0.0
            ],
            "head_waist" : [
                0.0,
                -0.0,
                -0.0,
                0.0
            ],
            "timeline" : 0.46
        },
        {
            "arm" : [
                0.0,
                -1.396,
                -0.0,
                -0.0,
                -0.0,
                -0.0,
                -0.07,
                -0.273,
                1.252,
                0.974,
                -0.278,
                0.0
            ],
            "head_waist" : [
                0.0,
                -0.0,
                -0.0,
                0.0
            ],
            "timeline" : 0.48
        },
        {
            "arm" : [
                0.0,
                -1.396,
                -0.0,
                -0.0,
                -0.0,
                -0.0,
                -0.071,
                -0.316,
                1.284,
                0.999,
                -0.285,
                0.0
            ],
            "head_waist" : [
                0.0,
                -0.0,
                -0.0,
                0.0
            ],
            "timeline" : 0.5
        },
        {
            "arm" : [
                0.0,
                -1.396,
                -0.0,
                -0.0,
                -0.0,
                -0.0,
                -0.076,
                -0.431,
                1.371,
                1.066,
                -0.305,
                0.0
            ],
            "head_waist" : [
                0.0,
                -0.0,
                -0.0,
                0.0
            ],
            "timeline" : 0.52
        },
        {
            "arm" : [
                0.0,
                -1.396,
                -0.0,
                -0.0,
                -0.0,
                -0.0,
                -0.078,
                -0.465,
                1.396,
                1.086,
                -0.31,
                0.0
            ],
            "head_waist" : [
                0.0,
                -0.0,
                -0.0,
                0.0
            ],
            "timeline" : 0.54
        },
        {
            "arm" : [
                0.0,
                -1.396,
                -0.0,
                -0.0,
                -0.0,
                -0.0,
                -0.081,
                -0.553,
                1.462,
                1.137,
                -0.325,
                0.0
            ],
            "head_waist" : [
                0.0,
                -0.0,
                -0.0,
                0.0
            ],
            "timeline" : 0.56
        },
        {
            "arm" : [
                0.0,
                -1.396,
                -0.0,
                -0.0,
                -0.0,
                -0.0,
                -0.082,
                -0.577,
                1.48,
                1.151,
                -0.329,
                0.0
            ],
            "head_waist" : [
                0.0,
                -0.0,
                -0.0,
                0.0
            ],
            "timeline" : 0.58
        },
        {
            "arm" : [
                0.0,
                -1.396,
                -0.0,
                -0.0,
                -0.0,
                -0.0,
                -0.085,
                -0.635,
                1.523,
                1.185,
                -0.339,
                0.0
            ],
            "head_waist" : [
                0.0,
                -0.0,
                -0.0,
                0.0
            ],
            "timeline" : 0.6
        },
        {
            "arm" : [
                0.0,
                -1.396,
                -0.0,
                -0.0,
                -0.0,
                -0.0,
                -0.085,
                -0.649,
                1.534,
                1.193,
                -0.341,
                0.0
            ],
            "head_waist" : [
                0.0,
                -0.0,
                -0.0,
                0.0
            ],
            "timeline" : 0.62
        },
        {
            "arm" : [
                0.0,
                -1.396,
                -0.0,
                -0.0,
                -0.0,
                -0.0,
                -0.087,
                -0.68,
                1.557,
                1.211,
                -0.346,
                0.0
            ],
            "head_waist" : [
                0.0,
                -0.0,
                -0.0,
                0.0
            ],
            "timeline" : 0.64
        },
        {
            "arm" : [
                0.0,
                -1.396,
                -0.0,
                -0.0,
                -0.0,
                -0.0,
                -0.087,
                -0.687,
                1.562,
                1.215,
                -0.347,
                0.0
            ],
            "head_waist" : [
                0.0,
                -0.0,
                -0.0,
                0.0
            ],
            "timeline" : 0.66
        },
        {
            "arm" : [
                0.0,
                -1.396,
                -0.0,
                -0.0,
                -0.0,
                -0.0,
                -0.087,
                -0.697,
                1.57,
                1.221,
                -0.349,
                0.0
            ],
            "head_waist" : [
                0.0,
                -0.0,
                -0.0,
                0.0
            ],
            "timeline" : 0.68
        },
        {
            "arm" : [
                0.0,
                -1.396,
                -0.0,
                -0.0,
                -0.0,
                -0.0,
                -0.087,
                -0.698,
                1.57,
                1.221,
                -0.349,
                0.0
            ],
            "head_waist" : [
                0.0,
                -0.0,
                -0.0,
                0.0
            ],
            "timeline" : 0.7
        },
        {
            "arm" : [
                0.0,
                -1.396,
                -0.0,
                -0.0,
                -0.0,
                -0.0,
                -0.087,
                -0.698,
                1.571,
                1.222,
                -0.349,
                0.0
            ],
            "head_waist" : [
                0.0,
                -0.0,
                -0.0,
                0.0
            ],
            "timeline" : 0.72
        },
        {
            "arm" : [
                0.0,
                -1.396,
                -0.0,
                -0.0,
                -0.0,
                -0.0,
                -0.087,
                -0.698,
                1.571,
                1.22,
                -0.349,
                0.0
            ],
            "head_waist" : [
                0.0,
                -0.0,
                -0.0,
                0.0
            ],
            "timeline" : 0.74
        },
        {
            "arm" : [
                0.0,
                -1.396,
                -0.0,
                -0.0,
                -0.0,
                -0.0,
                -0.087,
                -0.695,
                1.571,
                1.203,
                -0.349,
                0.0
            ],
            "head_waist" : [
                0.0,
                -0.0,
                -0.0,
                0.0
            ],
            "timeline" : 0.76
        },
        {
            "arm" : [
                0.0,
                -1.396,
                -0.0,
                -0.0,
                -0.0,
                -0.0,
                -0.087,
                -0.693,
                1.571,
                1.191,
                -0.349,
                0.0
            ],
            "head_waist" : [
                0.0,
                -0.0,
                -0.0,
                0.0
            ],
            "timeline" : 0.78
        },
        {
            "arm" : [
                0.0,
                -1.396,
                -0.0,
                -0.0,
                -0.0,
                -0.0,
                -0.087,
                -0.684,
                1.571,
                1.136,
                -0.349,
                0.0
            ],
            "head_waist" : [
                0.0,
                -0.0,
                -0.0,
                0.0
            ],
            "timeline" : 0.8
        },
        {
            "arm" : [
                0.0,
                -1.396,
                -0.0,
                -0.0,
                -0.0,
                -0.0,
                -0.087,
                -0.675,
                1.571,
                1.085,
                -0.349,
                0.0
            ],
            "head_waist" : [
                0.0,
                -0.0,
                -0.0,
                0.0
            ],
            "timeline" : 0.82
        },
        {
            "arm" : [
                0.0,
                -1.396,
                -0.0,
                -0.0,
                -0.0,
                -0.0,
                -0.087,
                -0.665,
                1.571,
                1.025,
                -0.349,
                0.0
            ],
            "head_waist" : [
                0.0,
                -0.0,
                -0.0,
                0.0
            ],
            "timeline" : 0.84
        },
        {
            "arm" : [
                0.0,
                -1.396,
                -0.0,
                -0.0,
                -0.0,
                -0.0,
                -0.087,
                -0.654,
                1.571,
                0.96,
                -0.349,
                0.0
            ],
            "head_waist" : [
                0.0,
                -0.0,
                -0.0,
                0.0
            ],
            "timeline" : 0.86
        },
        {
            "arm" : [
                0.0,
                -1.396,
                -0.0,
                -0.0,
                -0.0,
                -0.0,
                -0.087,
                -0.644,
                1.571,
                0.895,
                -0.349,
                0.0
            ],
            "head_waist" : [
                0.0,
                -0.0,
                -0.0,
                0.0
            ],
            "timeline" : 0.88
        },
        {
            "arm" : [
                0.0,
                -1.396,
                -0.0,
                -0.0,
                -0.0,
                -0.0,
                -0.087,
                -0.634,
                1.571,
                0.835,
                -0.349,
                0.0
            ],
            "head_waist" : [
                0.0,
                -0.0,
                -0.0,
                0.0
            ],
            "timeline" : 0.9
        },
        {
            "arm" : [
                0.0,
                -1.396,
                -0.0,
                -0.0,
                -0.0,
                -0.0,
                -0.087,
                -0.629,
                1.571,
                0.808,
                -0.349,
                0.0
            ],
            "head_waist" : [
                0.0,
                -0.0,
                -0.0,
                0.0
            ],
            "timeline" : 0.92
        },
        {
            "arm" : [
                0.0,
                -1.396,
                -0.0,
                -0.0,
                -0.0,
                -0.0,
                -0.087,
                -0.618,
                1.571,
                0.744,
                -0.349,
                0.0
            ],
            "head_waist" : [
                0.0,
                -0.0,
                -0.0,
                0.0
            ],
            "timeline" : 0.94
        },
        {
            "arm" : [
                0.0,
                -1.396,
                -0.0,
                -0.0,
                -0.0,
                -0.0,
                -0.087,
                -0.616,
                1.571,
                0.728,
                -0.349,
                0.0
            ],
            "head_waist" : [
                0.0,
                -0.0,
                -0.0,
                0.0
            ],
            "timeline" : 0.96
        },
        {
            "arm" : [
                0.0,
                -1.396,
                -0.0,
                -0.0,
                -0.0,
                -0.0,
                -0.087,
                -0.612,
                1.571,
                0.703,
                -0.349,
                0.0
            ],
            "head_waist" : [
                0.0,
                -0.0,
                -0.0,
                0.0
            ],
            "timeline" : 0.98
        },
        {
            "arm" : [
                0.0,
                -1.396,
                -0.0,
                -0.0,
                -0.0,
                -0.0,
                -0.087,
                -0.611,
                1.571,
                0.7,
                -0.349,
                0.0
            ],
            "head_waist" : [
                0.0,
                -0.0,
                -0.0,
                0.0
            ],
            "timeline" : 1.0
        },
        {
            "arm" : [
                0.0,
                -1.396,
                -0.0,
                -0.0,
                -0.0,
                -0.0,
                -0.087,
                -0.611,
                1.571,
                0.698,
                -0.349,
                0.0
            ],
            "head_waist" : [
                0.0,
                -0.0,
                -0.0,
                0.0
            ],
            "timeline" : 1.02
        },
        {
            "arm" : [
                0.0,
                -1.396,
                -0.0,
                -0.0,
                -0.0,
                -0.0,
                -0.087,
                -0.611,
                1.571,
                0.7,
                -0.349,
                0.0
            ],
            "head_waist" : [
                0.0,
                -0.0,
                -0.0,
                0.0
            ],
            "timeline" : 1.04
        },
        {
            "arm" : [
                0.0,
                -1.396,
                -0.0,
                -0.0,
                -0.0,
                -0.0,
                -0.087,
                -0.614,
                1.571,
                0.717,
                -0.349,
                0.0
            ],
            "head_waist" : [
                0.0,
                -0.0,
                -0.0,
                0.0
            ],
            "timeline" : 1.06
        },
        {
            "arm" : [
                0.0,
                -1.396,
                -0.0,
                -0.0,
                -0.0,
                -0.0,
                -0.087,
                -0.616,
                1.571,
                0.728,
                -0.349,
                0.0
            ],
            "head_waist" : [
                0.0,
                -0.0,
                -0.0,
                0.0
            ],
            "timeline" : 1.08
        },
        {
            "arm" : [
                0.0,
                -1.396,
                -0.0,
                -0.0,
                -0.0,
                -0.0,
                -0.087,
                -0.625,
                1.571,
                0.784,
                -0.349,
                0.0
            ],
            "head_waist" : [
                0.0,
                -0.0,
                -0.0,
                0.0
            ],
            "timeline" : 1.1
        },
        {
            "arm" : [
                0.0,
                -1.396,
                -0.0,
                -0.0,
                -0.0,
                -0.0,
                -0.087,
                -0.629,
                1.571,
                0.808,
                -0.349,
                0.0
            ],
            "head_waist" : [
                0.0,
                -0.0,
                -0.0,
                0.0
            ],
            "timeline" : 1.12
        },
        {
            "arm" : [
                0.0,
                -1.396,
                -0.0,
                -0.0,
                -0.0,
                -0.0,
                -0.087,
                -0.644,
                1.571,
                0.895,
                -0.349,
                0.0
            ],
            "head_waist" : [
                0.0,
                -0.0,
                -0.0,
                0.0
            ],
            "timeline" : 1.14
        },
        {
            "arm" : [
                0.0,
                -1.396,
                -0.0,
                -0.0,
                -0.0,
                -0.0,
                -0.087,
                -0.649,
                1.571,
                0.927,
                -0.349,
                0.0
            ],
            "head_waist" : [
                0.0,
                -0.0,
                -0.0,
                0.0
            ],
            "timeline" : 1.16
        },
        {
            "arm" : [
                0.0,
                -1.396,
                -0.0,
                -0.0,
                -0.0,
                -0.0,
                -0.087,
                -0.665,
                1.571,
                1.025,
                -0.349,
                0.0
            ],
            "head_waist" : [
                0.0,
                -0.0,
                -0.0,
                0.0
            ],
            "timeline" : 1.18
        },
        {
            "arm" : [
                0.0,
                -1.396,
                -0.0,
                -0.0,
                -0.0,
                -0.0,
                -0.087,
                -0.67,
                1.571,
                1.056,
                -0.349,
                0.0
            ],
            "head_waist" : [
                0.0,
                -0.0,
                -0.0,
                0.0
            ],
            "timeline" : 1.2
        },
        {
            "arm" : [
                0.0,
                -1.396,
                -0.0,
                -0.0,
                -0.0,
                -0.0,
                -0.087,
                -0.684,
                1.571,
                1.136,
                -0.349,
                0.0
            ],
            "head_waist" : [
                0.0,
                -0.0,
                -0.0,
                0.0
            ],
            "timeline" : 1.22
        },
        {
            "arm" : [
                0.0,
                -1.396,
                -0.0,
                -0.0,
                -0.0,
                -0.0,
                -0.087,
                -0.687,
                1.571,
                1.158,
                -0.349,
                0.0
            ],
            "head_waist" : [
                0.0,
                -0.0,
                -0.0,
                0.0
            ],
            "timeline" : 1.24
        },
        {
            "arm" : [
                0.0,
                -1.396,
                -0.0,
                -0.0,
                -0.0,
                -0.0,
                -0.087,
                -0.695,
                1.571,
                1.203,
                -0.349,
                0.0
            ],
            "head_waist" : [
                0.0,
                -0.0,
                -0.0,
                0.0
            ],
            "timeline" : 1.26
        },
        {
            "arm" : [
                0.0,
                -1.396,
                -0.0,
                -0.0,
                -0.0,
                -0.0,
                -0.087,
                -0.696,
                1.571,
                1.212,
                -0.349,
                0.0
            ],
            "head_waist" : [
                0.0,
                -0.0,
                -0.0,
                0.0
            ],
            "timeline" : 1.28
        },
        {
            "arm" : [
                0.0,
                -1.396,
                -0.0,
                -0.0,
                -0.0,
                -0.0,
                -0.087,
                -0.698,
                1.571,
                1.222,
                -0.349,
                0.0
            ],
            "head_waist" : [
                0.0,
                -0.0,
                -0.0,
                0.0
            ],
            "timeline" : 1.3
        },
        {
            "arm" : [
                0.0,
                -1.396,
                -0.0,
                -0.0,
                -0.0,
                -0.0,
                -0.087,
                -0.698,
                1.571,
                1.222,
                -0.349,
                0.0
            ],
            "head_waist" : [
                0.0,
                -0.0,
                -0.0,
                0.0
            ],
            "timeline" : 1.32
        },
        {
            "arm" : [
                0.0,
                -1.396,
                -0.0,
                -0.0,
                -0.0,
                -0.0,
                -0.087,
                -0.697,
                1.571,
                1.217,
                -0.349,
                0.0
            ],
            "head_waist" : [
                0.0,
                -0.0,
                -0.0,
                0.0
            ],
            "timeline" : 1.34
        },
        {
            "arm" : [
                0.0,
                -1.396,
                -0.0,
                -0.0,
                -0.0,
                -0.0,
                -0.087,
                -0.696,
                1.571,
                1.212,
                -0.349,
                0.0
            ],
            "head_waist" : [
                0.0,
                -0.0,
                -0.0,
                0.0
            ],
            "timeline" : 1.36
        },
        {
            "arm" : [
                0.0,
                -1.396,
                -0.0,
                -0.0,
                -0.0,
                -0.0,
                -0.087,
                -0.693,
                1.571,
                1.191,
                -0.349,
                0.0
            ],
            "head_waist" : [
                0.0,
                -0.0,
                -0.0,
                0.0
            ],
            "timeline" : 1.38
        },
        {
            "arm" : [
                0.0,
                -1.396,
                -0.0,
                -0.0,
                -0.0,
                -0.0,
                -0.087,
                -0.684,
                1.571,
                1.136,
                -0.349,
                0.0
            ],
            "head_waist" : [
                0.0,
                -0.0,
                -0.0,
                0.0
            ],
            "timeline" : 1.4
        },
        {
            "arm" : [
                0.0,
                -1.396,
                -0.0,
                -0.0,
                -0.0,
                -0.0,
                -0.087,
                -0.68,
                1.571,
                1.112,
                -0.349,
                0.0
            ],
            "head_waist" : [
                0.0,
                -0.0,
                -0.0,
                0.0
            ],
            "timeline" : 1.42
        },
        {
            "arm" : [
                0.0,
                -1.396,
                -0.0,
                -0.0,
                -0.0,
                -0.0,
                -0.087,
                -0.665,
                1.571,
                1.025,
                -0.349,
                0.0
            ],
            "head_waist" : [
                0.0,
                -0.0,
                -0.0,
                0.0
            ],
            "timeline" : 1.44
        },
        {
            "arm" : [
                0.0,
                -1.396,
                -0.0,
                -0.0,
                -0.0,
                -0.0,
                -0.087,
                -0.66,
                1.571,
                0.993,
                -0.349,
                0.0
            ],
            "head_waist" : [
                0.0,
                -0.0,
                -0.0,
                0.0
            ],
            "timeline" : 1.46
        },
        {
            "arm" : [
                0.0,
                -1.396,
                -0.0,
                -0.0,
                -0.0,
                -0.0,
                -0.087,
                -0.644,
                1.571,
                0.895,
                -0.349,
                0.0
            ],
            "head_waist" : [
                0.0,
                -0.0,
                -0.0,
                0.0
            ],
            "timeline" : 1.48
        },
        {
            "arm" : [
                0.0,
                -1.396,
                -0.0,
                -0.0,
                -0.0,
                -0.0,
                -0.087,
                -0.639,
                1.571,
                0.864,
                -0.349,
                0.0
            ],
            "head_waist" : [
                0.0,
                -0.0,
                -0.0,
                0.0
            ],
            "timeline" : 1.5
        },
        {
            "arm" : [
                0.0,
                -1.396,
                -0.0,
                -0.0,
                -0.0,
                -0.0,
                -0.087,
                -0.625,
                1.571,
                0.784,
                -0.349,
                0.0
            ],
            "head_waist" : [
                0.0,
                -0.0,
                -0.0,
                0.0
            ],
            "timeline" : 1.52
        },
        {
            "arm" : [
                0.0,
                -1.396,
                -0.0,
                -0.0,
                -0.0,
                -0.0,
                -0.087,
                -0.618,
                1.571,
                0.744,
                -0.349,
                0.0
            ],
            "head_waist" : [
                0.0,
                -0.0,
                -0.0,
                0.0
            ],
            "timeline" : 1.54
        },
        {
            "arm" : [
                0.0,
                -1.396,
                -0.0,
                -0.0,
                -0.0,
                -0.0,
                -0.087,
                -0.618,
                1.571,
                0.744,
                -0.349,
                0.0
            ],
            "head_waist" : [
                0.0,
                -0.0,
                -0.0,
                0.0
            ],
            "timeline" : 1.56
        },
        {
            "arm" : [
                0.0,
                -1.396,
                -0.0,
                -0.0,
                -0.0,
                -0.0,
                -0.087,
                -0.612,
                1.571,
                0.703,
                -0.349,
                0.0
            ],
            "head_waist" : [
                0.0,
                -0.0,
                -0.0,
                0.0
            ],
            "timeline" : 1.58
        },
        {
            "arm" : [
                0.0,
                -1.396,
                -0.0,
                -0.0,
                -0.0,
                -0.0,
                -0.087,
                -0.611,
                1.571,
                0.7,
                -0.349,
                0.0
            ],
            "head_waist" : [
                0.0,
                -0.0,
                -0.0,
                0.0
            ],
            "timeline" : 1.6
        },
        {
            "arm" : [
                0.0,
                -1.396,
                -0.0,
                -0.0,
                -0.0,
                -0.0,
                -0.087,
                -0.611,
                1.571,
                0.698,
                -0.349,
                0.0
            ],
            "head_waist" : [
                0.0,
                -0.0,
                -0.0,
                0.0
            ],
            "timeline" : 1.62
        },
        {
            "arm" : [
                0.0,
                -1.396,
                -0.0,
                -0.0,
                -0.0,
                -0.0,
                -0.087,
                -0.611,
                1.571,
                0.7,
                -0.349,
                0.0
            ],
            "head_waist" : [
                0.0,
                -0.0,
                -0.0,
                0.0
            ],
            "timeline" : 1.64
        },
        {
            "arm" : [
                0.0,
                -1.396,
                -0.0,
                -0.0,
                -0.0,
                -0.0,
                -0.087,
                -0.614,
                1.571,
                0.717,
                -0.349,
                0.0
            ],
            "head_waist" : [
                0.0,
                -0.0,
                -0.0,
                0.0
            ],
            "timeline" : 1.66
        },
        {
            "arm" : [
                0.0,
                -1.396,
                -0.0,
                -0.0,
                -0.0,
                -0.0,
                -0.087,
                -0.616,
                1.571,
                0.728,
                -0.349,
                0.0
            ],
            "head_waist" : [
                0.0,
                -0.0,
                -0.0,
                0.0
            ],
            "timeline" : 1.68
        },
        {
            "arm" : [
                0.0,
                -1.396,
                -0.0,
                -0.0,
                -0.0,
                -0.0,
                -0.087,
                -0.622,
                1.571,
                0.762,
                -0.349,
                0.0
            ],
            "head_waist" : [
                0.0,
                -0.0,
                -0.0,
                0.0
            ],
            "timeline" : 1.7
        },
        {
            "arm" : [
                0.0,
                -1.396,
                -0.0,
                -0.0,
                -0.0,
                -0.0,
                -0.087,
                -0.634,
                1.571,
                0.835,
                -0.349,
                0.0
            ],
            "head_waist" : [
                0.0,
                -0.0,
                -0.0,
                0.0
            ],
            "timeline" : 1.72
        },
        {
            "arm" : [
                0.0,
                -1.396,
                -0.0,
                -0.0,
                -0.0,
                -0.0,
                -0.087,
                -0.639,
                1.571,
                0.864,
                -0.349,
                0.0
            ],
            "head_waist" : [
                0.0,
                -0.0,
                -0.0,
                0.0
            ],
            "timeline" : 1.74
        },
        {
            "arm" : [
                0.0,
                -1.396,
                -0.0,
                -0.0,
                -0.0,
                -0.0,
                -0.087,
                -0.654,
                1.571,
                0.96,
                -0.349,
                0.0
            ],
            "head_waist" : [
                0.0,
                -0.0,
                -0.0,
                0.0
            ],
            "timeline" : 1.76
        },
        {
            "arm" : [
                0.0,
                -1.396,
                -0.0,
                -0.0,
                -0.0,
                -0.0,
                -0.087,
                -0.66,
                1.571,
                0.993,
                -0.349,
                0.0
            ],
            "head_waist" : [
                0.0,
                -0.0,
                -0.0,
                0.0
            ],
            "timeline" : 1.78
        },
        {
            "arm" : [
                0.0,
                -1.396,
                -0.0,
                -0.0,
                -0.0,
                -0.0,
                -0.087,
                -0.675,
                1.571,
                1.085,
                -0.349,
                0.0
            ],
            "head_waist" : [
                0.0,
                -0.0,
                -0.0,
                0.0
            ],
            "timeline" : 1.8
        },
        {
            "arm" : [
                0.0,
                -1.396,
                -0.0,
                -0.0,
                -0.0,
                -0.0,
                -0.087,
                -0.684,
                1.571,
                1.136,
                -0.349,
                0.0
            ],
            "head_waist" : [
                0.0,
                -0.0,
                -0.0,
                0.0
            ],
            "timeline" : 1.82
        },
        {
            "arm" : [
                0.0,
                -1.396,
                -0.0,
                -0.0,
                -0.0,
                -0.0,
                -0.087,
                -0.687,
                1.571,
                1.158,
                -0.349,
                0.0
            ],
            "head_waist" : [
                0.0,
                -0.0,
                -0.0,
                0.0
            ],
            "timeline" : 1.84
        },
        {
            "arm" : [
                0.0,
                -1.396,
                -0.0,
                -0.0,
                -0.0,
                -0.0,
                -0.087,
                -0.695,
                1.571,
                1.203,
                -0.349,
                0.0
            ],
            "head_waist" : [
                0.0,
                -0.0,
                -0.0,
                0.0
            ],
            "timeline" : 1.86
        },
        {
            "arm" : [
                0.0,
                -1.396,
                -0.0,
                -0.0,
                -0.0,
                -0.0,
                -0.087,
                -0.696,
                1.571,
                1.212,
                -0.349,
                0.0
            ],
            "head_waist" : [
                0.0,
                -0.0,
                -0.0,
                0.0
            ],
            "timeline" : 1.88
        },
        {
            "arm" : [
                0.0,
                -1.396,
                -0.0,
                -0.0,
                -0.0,
                -0.0,
                -0.087,
                -0.698,
                1.571,
                1.222,
                -0.349,
                0.0
            ],
            "head_waist" : [
                0.0,
                -0.0,
                -0.0,
                0.0
            ],
            "timeline" : 1.9
        },
        {
            "arm" : [
                0.0,
                -1.396,
                -0.0,
                -0.0,
                -0.0,
                -0.0,
                -0.087,
                -0.698,
                1.571,
                1.222,
                -0.349,
                0.0
            ],
            "head_waist" : [
                0.0,
                -0.0,
                -0.0,
                0.0
            ],
            "timeline" : 1.92
        },
        {
            "arm" : [
                0.0,
                -1.396,
                -0.0,
                -0.0,
                -0.0,
                -0.0,
                -0.087,
                -0.698,
                1.57,
                1.221,
                -0.349,
                0.0
            ],
            "head_waist" : [
                0.0,
                -0.0,
                -0.0,
                0.0
            ],
            "timeline" : 1.94
        },
        {
            "arm" : [
                0.0,
                -1.396,
                -0.0,
                -0.0,
                -0.0,
                -0.0,
                -0.087,
                -0.691,
                1.566,
                1.218,
                -0.348,
                0.0
            ],
            "head_waist" : [
                0.0,
                -0.0,
                -0.0,
                0.0
            ],
            "timeline" : 1.96
        },
        {
            "arm" : [
                0.0,
                -1.396,
                -0.0,
                -0.0,
                -0.0,
                -0.0,
                -0.087,
                -0.68,
                1.557,
                1.211,
                -0.346,
                0.0
            ],
            "head_waist" : [
                0.0,
                -0.0,
                -0.0,
                0.0
            ],
            "timeline" : 1.98
        },
        {
            "arm" : [
                0.0,
                -1.396,
                -0.0,
                -0.0,
                -0.0,
                -0.0,
                -0.086,
                -0.672,
                1.551,
                1.206,
                -0.345,
                0.0
            ],
            "head_waist" : [
                0.0,
                -0.0,
                -0.0,
                0.0
            ],
            "timeline" : 2.0
        },
        {
            "arm" : [
                0.0,
                -1.396,
                -0.0,
                -0.0,
                -0.0,
                -0.0,
                -0.085,
                -0.635,
                1.523,
                1.185,
                -0.339,
                0.0
            ],
            "head_waist" : [
                0.0,
                -0.0,
                -0.0,
                0.0
            ],
            "timeline" : 2.02
        },
        {
            "arm" : [
                0.0,
                -1.396,
                -0.0,
                -0.0,
                -0.0,
                -0.0,
                -0.084,
                -0.618,
                1.511,
                1.175,
                -0.336,
                0.0
            ],
            "head_waist" : [
                0.0,
                -0.0,
                -0.0,
                0.0
            ],
            "timeline" : 2.04
        },
        {
            "arm" : [
                0.0,
                -1.396,
                -0.0,
                -0.0,
                -0.0,
                -0.0,
                -0.081,
                -0.553,
                1.462,
                1.137,
                -0.325,
                0.0
            ],
            "head_waist" : [
                0.0,
                -0.0,
                -0.0,
                0.0
            ],
            "timeline" : 2.06
        },
        {
            "arm" : [
                0.0,
                -1.396,
                -0.0,
                -0.0,
                -0.0,
                -0.0,
                -0.08,
                -0.526,
                1.442,
                1.121,
                -0.32,
                0.0
            ],
            "head_waist" : [
                0.0,
                -0.0,
                -0.0,
                0.0
            ],
            "timeline" : 2.08
        },
        {
            "arm" : [
                0.0,
                -1.396,
                -0.0,
                -0.0,
                -0.0,
                -0.0,
                -0.076,
                -0.431,
                1.371,
                1.066,
                -0.305,
                0.0
            ],
            "head_waist" : [
                0.0,
                -0.0,
                -0.0,
                0.0
            ],
            "timeline" : 2.1
        },
        {
            "arm" : [
                0.0,
                -1.396,
                -0.0,
                -0.0,
                -0.0,
                -0.0,
                -0.075,
                -0.395,
                1.343,
                1.045,
                -0.299,
                0.0
            ],
            "head_waist" : [
                0.0,
                -0.0,
                -0.0,
                0.0
            ],
            "timeline" : 2.12
        },
        {
            "arm" : [
                0.0,
                -1.396,
                -0.0,
                -0.0,
                -0.0,
                -0.0,
                -0.07,
                -0.273,
                1.252,
                0.974,
                -0.278,
                0.0
            ],
            "head_waist" : [
                0.0,
                -0.0,
                -0.0,
                0.0
            ],
            "timeline" : 2.14
        },
        {
            "arm" : [
                0.0,
                -1.396,
                -0.0,
                -0.0,
                -0.0,
                -0.0,
                -0.068,
                -0.229,
                1.219,
                0.948,
                -0.271,
                0.0
            ],
            "head_waist" : [
                0.0,
                -0.0,
                -0.0,
                0.0
            ],
            "timeline" : 2.16
        },
        {
            "arm" : [
                0.0,
                -1.396,
                -0.0,
                -0.0,
                -0.0,
                -0.0,
                -0.062,
                -0.084,
                1.11,
                0.864,
                -0.247,
                0.0
            ],
            "head_waist" : [
                0.0,
                -0.0,
                -0.0,
                0.0
            ],
            "timeline" : 2.18
        },
        {
            "arm" : [
                0.0,
                -1.396,
                -0.0,
                -0.0,
                -0.0,
                -0.0,
                -0.06,
                -0.033,
                1.072,
                0.834,
                -0.238,
                0.0
            ],
            "head_waist" : [
                0.0,
                -0.0,
                -0.0,
                0.0
            ],
            "timeline" : 2.2
        },
        {
            "arm" : [
                0.0,
                -1.396,
                -0.0,
                -0.0,
                -0.0,
                -0.0,
                -0.053,
                0.127,
                0.952,
                0.741,
                -0.212,
                0.0
            ],
            "head_waist" : [
                0.0,
                -0.0,
                -0.0,
                0.0
            ],
            "timeline" : 2.22
        },
        {
            "arm" : [
                0.0,
                -1.396,
                -0.0,
                -0.0,
                -0.0,
                -0.0,
                -0.051,
                0.182,
                0.911,
                0.709,
                -0.202,
                0.0
            ],
            "head_waist" : [
                0.0,
                -0.0,
                -0.0,
                0.0
            ],
            "timeline" : 2.24
        },
        {
            "arm" : [
                0.0,
                -1.396,
                -0.0,
                -0.0,
                -0.0,
                -0.0,
                -0.044,
                0.349,
                0.785,
                0.611,
                -0.175,
                0.0
            ],
            "head_waist" : [
                0.0,
                -0.0,
                -0.0,
                0.0
            ],
            "timeline" : 2.26
        },
        {
            "arm" : [
                0.0,
                -1.396,
                -0.0,
                -0.0,
                -0.0,
                -0.0,
                -0.041,
                0.405,
                0.743,
                0.578,
                -0.165,
                0.0
            ],
            "head_waist" : [
                0.0,
                -0.0,
                -0.0,
                0.0
            ],
            "timeline" : 2.28
        },
        {
            "arm" : [
                0.0,
                -1.396,
                -0.0,
                -0.0,
                -0.0,
                -0.0,
                -0.034,
                0.572,
                0.619,
                0.481,
                -0.137,
                0.0
            ],
            "head_waist" : [
                0.0,
                -0.0,
                -0.0,
                0.0
            ],
            "timeline" : 2.3
        },
        {
            "arm" : [
                0.0,
                -1.396,
                -0.0,
                -0.0,
                -0.0,
                -0.0,
                -0.032,
                0.626,
                0.578,
                0.449,
                -0.128,
                0.0
            ],
            "head_waist" : [
                0.0,
                -0.0,
                -0.0,
                0.0
            ],
            "timeline" : 2.32
        },
        {
            "arm" : [
                0.0,
                -1.396,
                -0.0,
                -0.0,
                -0.0,
                -0.0,
                -0.026,
                0.782,
                0.46,
                0.358,
                -0.102,
                0.0
            ],
            "head_waist" : [
                0.0,
                -0.0,
                -0.0,
                0.0
            ],
            "timeline" : 2.34
        },
        {
            "arm" : [
                0.0,
                -1.396,
                -0.0,
                -0.0,
                -0.0,
                -0.0,
                -0.024,
                0.832,
                0.423,
                0.329,
                -0.094,
                0.0
            ],
            "head_waist" : [
                0.0,
                -0.0,
                -0.0,
                0.0
            ],
            "timeline" : 2.36
        },
        {
            "arm" : [
                0.0,
                -1.396,
                -0.0,
                -0.0,
                -0.0,
                -0.0,
                -0.018,
                0.971,
                0.319,
                0.248,
                -0.071,
                0.0
            ],
            "head_waist" : [
                0.0,
                -0.0,
                -0.0,
                0.0
            ],
            "timeline" : 2.38
        },
        {
            "arm" : [
                0.0,
                -1.396,
                -0.0,
                -0.0,
                -0.0,
                -0.0,
                -0.016,
                1.014,
                0.287,
                0.223,
                -0.064,
                0.0
            ],
            "head_waist" : [
                0.0,
                -0.0,
                -0.0,
                0.0
            ],
            "timeline" : 2.4
        },
        {
            "arm" : [
                0.0,
                -1.396,
                -0.0,
                -0.0,
                -0.0,
                -0.0,
                -0.011,
                1.129,
                0.2,
                0.156,
                -0.044,
                0.0
            ],
            "head_waist" : [
                0.0,
                -0.0,
                -0.0,
                0.0
            ],
            "timeline" : 2.42
        },
        {
            "arm" : [
                0.0,
                -1.396,
                -0.0,
                -0.0,
                -0.0,
                -0.0,
                -0.01,
                1.163,
                0.175,
                0.136,
                -0.039,
                0.0
            ],
            "head_waist" : [
                0.0,
                -0.0,
                -0.0,
                0.0
            ],
            "timeline" : 2.44
        },
        {
            "arm" : [
                0.0,
                -1.396,
                -0.0,
                -0.0,
                -0.0,
                -0.0,
                -0.006,
                1.251,
                0.109,
                0.085,
                -0.024,
                0.0
            ],
            "head_waist" : [
                0.0,
                -0.0,
                -0.0,
                0.0
            ],
            "timeline" : 2.46
        },
        {
            "arm" : [
                0.0,
                -1.396,
                -0.0,
                -0.0,
                -0.0,
                -0.0,
                -0.005,
                1.275,
                0.091,
                0.071,
                -0.02,
                0.0
            ],
            "head_waist" : [
                0.0,
                -0.0,
                -0.0,
                0.0
            ],
            "timeline" : 2.48
        },
        {
            "arm" : [
                0.0,
                -1.396,
                -0.0,
                -0.0,
                -0.0,
                -0.0,
                -0.003,
                1.333,
                0.047,
                0.037,
                -0.011,
                0.0
            ],
            "head_waist" : [
                0.0,
                -0.0,
                -0.0,
                0.0
            ],
            "timeline" : 2.5
        },
        {
            "arm" : [
                0.0,
                -1.396,
                -0.0,
                -0.0,
                -0.0,
                -0.0,
                -0.002,
                1.348,
                0.037,
                0.028,
                -0.008,
                0.0
            ],
            "head_waist" : [
                0.0,
                -0.0,
                -0.0,
                0.0
            ],
            "timeline" : 2.52
        },
        {
            "arm" : [
                0.0,
                -1.396,
                -0.0,
                -0.0,
                -0.0,
                -0.0,
                -0.001,
                1.378,
                0.013,
                0.01,
                -0.003,
                0.0
            ],
            "head_waist" : [
                0.0,
                -0.0,
                -0.0,
                0.0
            ],
            "timeline" : 2.54
        },
        {
            "arm" : [
                0.0,
                -1.396,
                -0.0,
                -0.0,
                -0.0,
                -0.0,
                -0.0,
                1.385,
                0.009,
                0.007,
                -0.002,
                0.0
            ],
            "head_waist" : [
                0.0,
                -0.0,
                -0.0,
                0.0
            ],
            "timeline" : 2.56
        }
    ],
    "name" : "hello"
}